[
    {
        "name": "Open de Picardie",
        "location": "Gouvieux",
        "start_date": "2025-11-12",
        "end_date": "2025-11-15",
        "number_of_rounds": 4,
        "current_round": "",
        "rounds": [],
        "players": [
            "AB12345",
            "AB12346",
            "AB12348",
            "AB12349"
        ],
        "description": "Tournoi test pour debug",
        "status": "À venir",
        "tournament_id": "2859"
    },
    {
        "name": "Open des Hauts de France",
        "location": "Chantilly",
        "start_date": "2025-11-21",
        "end_date": "2025-11-25",
        "number_of_rounds": 4,
        "current_round": "",
        "rounds": [],
        "players": [],
        "description": "Tournoi tes pour débug et mise en place du CRUD",
        "status": "À venir",
        "tournament_id": "1e19"
    },
    {
        "name": "Open d'Ile de France",
        "location": "Paris",
        "start_date": "2025-12-01",
        "end_date": "2025-12-05",
        "number_of_rounds": 3,
        "current_round": 1,
        "rounds": [],
        "players": [
            "AB12345",
            "AB12346",
            "AB12347",
            "AB12348"
        ],
        "description": "Tournoi test pour debug",
        "status": "En cours",
        "tournament_id": "2adc"
    },
    {
        "name": "Open du Testing",
        "location": "Testlandia",
        "start_date": "2025-10-25",
        "end_date": "2025-10-27",
        "number_of_rounds": 7,
        "current_round": 1,
        "rounds": [
            {
                "name": "Round 1",
                "round_id": "5a93",
                "start_date": "2025-10-06",
                "start_time": "17:47:24",
                "end_date": null,
                "end_time": null,
                "matches": [
                    [
                        [
                            "AB12352",
                            0.5
                        ],
                        [
                            "AB12349",
                            0.5
                        ]
                    ],
                    [
                        [
                            "EF57832",
                            1.0
                        ],
                        [
                            "FE34523",
                            0
                        ]
                    ],
                    [
                        [
                            "DM32456",
                            1.0
                        ],
                        [
                            "AB12353",
                            0
                        ]
                    ],
                    [
                        [
                            "AB12348",
                            0.0
                        ],
                        [
                            "FG97643",
                            1
                        ]
                    ]
                ],
                "status": "Terminé"
            }
        ],
        "players": [
            "FG97643",
            "DM32456",
            "EF57832",
            "FE34523",
            "AB12352",
            "AB12353",
            "AB12349",
            "AB12348"
        ],
        "description": "Ceci est la toute nouvelle description du tournoi",
        "status": "En cours",
        "tournament_id": "34c2"
    }
]